AUTHORS
INSTALL
LICENSE
MANIFEST.in
README.rst
dev_requirements.txt
requirements.txt
setup.cfg
setup.py
doc/.gitignore
doc/Makefile
doc/common_gotchas.rst
doc/conf.py
doc/developer.rst
doc/features.rst
doc/html_coder.rst
doc/index.rst
doc/quickstart.rst
doc/reference.rst
doc/settings.rst
doc/img/cms_models.png
doc/img/core_models.png
doc/img/photos_models.png
doc/img/welcomescreen.png
doc/plugins/boxes.rst
doc/plugins/custom_urls.rst
doc/plugins/index.rst
doc/plugins/listing_handlers.rst
doc/plugins/models.rst
doc/plugins/related_finders.rst
doc/reference/middleware.rst
doc/reference/models.rst
doc/reference/related_finders.rst
doc/reference/templates.rst
doc/reference/templatetags.rst
doc/reference/views.rst
ella/__init__.py
ella.egg-info/PKG-INFO
ella.egg-info/SOURCES.txt
ella.egg-info/dependency_links.txt
ella.egg-info/requires.txt
ella.egg-info/top_level.txt
ella/api/__init__.py
ella/api/conf.py
ella/api/middleware.py
ella/api/register.py
ella/api/serialization.py
ella/api/serializers.py
ella/articles/__init__.py
ella/articles/admin.py
ella/articles/models.py
ella/articles/newman_admin.py
ella/articles/locale/cs/LC_MESSAGES/django.mo
ella/articles/locale/cs/LC_MESSAGES/django.po
ella/articles/migrations/0001_initial.py
ella/articles/migrations/0002_add_field_article_content.py
ella/articles/migrations/0003_remove_contents.py
ella/articles/migrations/0004_remove_infobox.py
ella/articles/migrations/0005_move_updated_to_publishable.py
ella/articles/migrations/0006_auto__del_field_article_updated__del_field_article_created__del_field_.py
ella/articles/migrations/__init__.py
ella/core/__init__.py
ella/core/admin.py
ella/core/box.py
ella/core/conf.py
ella/core/context_processors.py
ella/core/custom_urls.py
ella/core/feeds.py
ella/core/managers.py
ella/core/middleware.py
ella/core/newman_admin.py
ella/core/register.py
ella/core/related_finders.py
ella/core/signals.py
ella/core/tasks.py
ella/core/urls.py
ella/core/views.py
ella/core/cache/__init__.py
ella/core/cache/fields.py
ella/core/cache/redis.py
ella/core/cache/utils.py
ella/core/locale/cs/LC_MESSAGES/django.mo
